{
    "complication": {
        "1-3": {
            "name": "Recursos",
            "diceRangeMin": 1,
            "diceRangeMax": 3,
            "complicationKey": "resources"
        },
        "4-6": {
            "name": "Vitimas",
            "diceRangeMin": 4,
            "diceRangeMax": 6,
            "complicationKey": "victims"
        },
        "7-8": {
            "name": "Organização",
            "diceRangeMin": 7,
            "diceRangeMax": 8,
            "complicationKey": "organization"
        },
        "9-9": {
            "name": "Miraculoso",
            "diceRangeMin": 9,
            "diceRangeMax": 9,
            "complicationKey": "miraculous"
        },
        "10-12": {
            "name": "Ambiente hostil",
            "diceRangeMin": 10,
            "diceRangeMax": 12,
            "complicationKey": "hostileEnv"
        },
        "13-13": {
            "name": "Inusitado",
            "diceRangeMin": 13,
            "diceRangeMax": 13,
            "complicationKey": "unusual"
        },
        "14-15": {
            "name": "Problemas diplomáticos",
            "diceRangeMin": 14,
            "diceRangeMax": 15,
            "complicationKey": "diplomaticIssue"
        },
        "16-16": {
            "name": "Proteção",
            "diceRangeMin": 16,
            "diceRangeMax": 16,
            "complicationKey": "protection"
        },
        "17-17": {
            "name": "Contratempo amistoso",
            "diceRangeMin": 17,
            "diceRangeMax": 17,
            "complicationKey": "friendlyAgainstTime"
        },
        "18-20": {
            "name": "Encontro hostil",
            "diceRangeMin": 18,
            "diceRangeMax": 20,
            "complicationKey": "hostileMeeting"
        }
    },
    "resources": {
        "1-1": {
            "name": "Um grande tesouro está em risco",
            "diceRangeMin": 1,
            "diceRangeMax": 1
        },
        "2-2": {
            "name": "O inimigo possui recursos infindáveis",
            "diceRangeMin": 2,
            "diceRangeMax": 2
        },
        "3-3": {
            "name": "As armas dos aventureiros não são eficazes",
            "diceRangeMin": 3,
            "diceRangeMax": 3
        },
        "4-4": {
            "name": "Algo torna a magia mais caótica",
            "diceRangeMin": 4,
            "diceRangeMax": 4
        },
        "5-5": {
            "name": "Tentativas de roubo",
            "diceRangeMin": 5,
            "diceRangeMax": 5
        },
        "6-6": {
            "name": "Fonte de água/comida contaminada",
            "diceRangeMin": 6,
            "diceRangeMax": 6
        },
        "7-7": {
            "name": "Artefato mágico fora de controle",
            "diceRangeMin": 7,
            "diceRangeMax": 7
        },
        "8-8": {
            "name": "Todos os tesouros são bugigangas",
            "diceRangeMin": 8,
            "diceRangeMax": 8
        },
        "9-9": {
            "name": "Crise econômica",
            "diceRangeMin": 9,
            "diceRangeMax": 9
        },
        "10-10": {
            "name": "Tesouro amaldiçoado",
            "diceRangeMin": 10,
            "diceRangeMax": 10
        }
    },
    "victims": {
        "1-1": {
            "name": "Grande número de inocentes afetados",
            "diceRangeMin": 1,
            "diceRangeMax": 1
        },
        "2-2": {
            "name": "Rival afetado que pede ajuda",
            "diceRangeMin": 2,
            "diceRangeMax": 2
        },
        "3-3": {
            "name": "Nobre orgulhoso",
            "diceRangeMin": 3,
            "diceRangeMax": 3
        },
        "4-4": {
            "name": "Entidade sobrenatural",
            "diceRangeMin": 4,
            "diceRangeMax": 4
        },
        "5-5": {
            "name": "Inocente levando a culpa",
            "diceRangeMin": 5,
            "diceRangeMax": 5
        },
        "6-6": {
            "name": "Criatura amada em perigo",
            "diceRangeMin": 6,
            "diceRangeMax": 6
        },
        "7-7": {
            "name": "Vitimas agem como vilões",
            "diceRangeMin": 7,
            "diceRangeMax": 7
        },
        "8-8": {
            "name": "Reféns com risco de morte",
            "diceRangeMin": 8,
            "diceRangeMax": 8
        },
        "9-9": {
            "name": "Refugiados de zona de conflito",
            "diceRangeMin": 9,
            "diceRangeMax": 9
        },
        "10-10": {
            "name": "Crianças/filhos do inimigo afetados",
            "diceRangeMin": 10,
            "diceRangeMax": 10
        }
    },
    "organization": {
        "1-1": {
            "name": "Grupo rival de aventureiros",
            "diceRangeMin": 1,
            "diceRangeMax": 1
        },
        "2-2": {
            "name": "Grupo de mercenários",
            "diceRangeMin": 2,
            "diceRangeMax": 2
        },
        "3-3": {
            "name": "Casa nobre que quer se beneficiar",
            "diceRangeMin": 3,
            "diceRangeMax": 3
        },
        "4-4": {
            "name": "Seita religiosa",
            "diceRangeMin": 4,
            "diceRangeMax": 4
        },
        "5-5": {
            "name": "Facção criminosa",
            "diceRangeMin": 5,
            "diceRangeMax": 5
        },
        "6-6": {
            "name": "Clã/família de grande renome",
            "diceRangeMin": 6,
            "diceRangeMax": 6
        },
        "7-7": {
            "name": "Sindicato de mercadores",
            "diceRangeMin": 7,
            "diceRangeMax": 7
        },
        "8-8": {
            "name": "Realeza é contra a conclusão do objetivo",
            "diceRangeMin": 8,
            "diceRangeMax": 8
        },
        "9-9": {
            "name": "Interesse direto da guilda",
            "diceRangeMin": 9,
            "diceRangeMax": 9
        },
        "10-10": {
            "name": "Revolucionários tem o mesmo objetivo",
            "diceRangeMin": 10,
            "diceRangeMax": 10
        }
    },
    "miraculous": {
        "1-1": {
            "name": "Maldição ancestral",
            "diceRangeMin": 1,
            "diceRangeMax": 1
        },
        "2-2": {
            "name": "Local sagrado para uma cultura",
            "diceRangeMin": 2,
            "diceRangeMax": 2
        },
        "3-3": {
            "name": "Energia corrosiva",
            "diceRangeMin": 3,
            "diceRangeMax": 3
        },
        "4-4": {
            "name": "A magia parece ter vida própria",
            "diceRangeMin": 4,
            "diceRangeMax": 4
        },
        "5-5": {
            "name": "Almas penadas",
            "diceRangeMin": 5,
            "diceRangeMax": 5
        },
        "6-6": {
            "name": "Antigo mal desperta",
            "diceRangeMin": 6,
            "diceRangeMax": 6
        },
        "7-7": {
            "name": "Tempestade de neve não natural",
            "diceRangeMin": 7,
            "diceRangeMax": 7
        },
        "8-8": {
            "name": "Objetos mágicos tem mal funcionamento",
            "diceRangeMin": 8,
            "diceRangeMax": 8
        },
        "9-9": {
            "name": "Comunicação impossível",
            "diceRangeMin": 9,
            "diceRangeMax": 9
        },
        "10-10": {
            "name": "Magia impede de chegar ao local",
            "diceRangeMin": 10,
            "diceRangeMax": 10
        }
    },
    "hostileEnv": {
        "1-1": {
            "name": "Difícil acesso",
            "diceRangeMin": 1,
            "diceRangeMax": 1
        },
        "2-2": {
            "name": "Habitantes hostis",
            "diceRangeMin": 2,
            "diceRangeMax": 2
        },
        "3-3": {
            "name": "Armadilhas mortais",
            "diceRangeMin": 3,
            "diceRangeMax": 3
        },
        "4-4": {
            "name": "Emboscadas frequentes",
            "diceRangeMin": 4,
            "diceRangeMax": 4
        },
        "5-5": {
            "name": "Ar rarefeito",
            "diceRangeMin": 5,
            "diceRangeMax": 5
        },
        "6-6": {
            "name": "Canibais agressivos",
            "diceRangeMin": 6,
            "diceRangeMax": 6
        },
        "7-7": {
            "name": "Toxinas nocivas",
            "diceRangeMin": 7,
            "diceRangeMax": 7
        },
        "8-8": {
            "name": "Profundezas oceânicas",
            "diceRangeMin": 8,
            "diceRangeMax": 8
        },
        "9-9": {
            "name": "Tempestades frequentes",
            "diceRangeMin": 9,
            "diceRangeMax": 9
        },
        "10-10": {
            "name": "Temperaturas extremas",
            "diceRangeMin": 10,
            "diceRangeMax": 10
        }
    },
    "unusual": {
        "1-1": {
            "name": "Dividido em 4 partes",
            "diceRangeMin": 1,
            "diceRangeMax": 1
        },
        "2-2": {
            "name": "Não existe/está nesse plano",
            "diceRangeMin": 2,
            "diceRangeMax": 2
        },
        "3-3": {
            "name": "Atitudes questionáveis",
            "diceRangeMin": 3,
            "diceRangeMax": 3
        },
        "4-4": {
            "name": "Disfarce imperceptível",
            "diceRangeMin": 4,
            "diceRangeMax": 4
        },
        "5-5": {
            "name": "Está em constante movimento",
            "diceRangeMin": 5,
            "diceRangeMax": 5
        },
        "6-6": {
            "name": "Informação equivocada",
            "diceRangeMin": 6,
            "diceRangeMax": 6
        },
        "7-7": {
            "name": "O contratante desaparece",
            "diceRangeMin": 7,
            "diceRangeMax": 7
        },
        "8-8": {
            "name": "Completamente esquecido",
            "diceRangeMin": 8,
            "diceRangeMax": 8
        },
        "9-9": {
            "name": "Memorias roubadas",
            "diceRangeMin": 9,
            "diceRangeMax": 9
        },
        "10-10": {
            "name": "Aliado confundido com inimigo",
            "diceRangeMin": 10,
            "diceRangeMax": 10
        }
    },
    "diplomaticIssue": {
        "1-1": {
            "name": "Problemas de jurisdição",
            "diceRangeMin": 1,
            "diceRangeMax": 1
        },
        "2-2": {
            "name": "Interferência política",
            "diceRangeMin": 2,
            "diceRangeMax": 2
        },
        "3-3": {
            "name": "Disputas de poder",
            "diceRangeMin": 3,
            "diceRangeMax": 3
        },
        "4-4": {
            "name": "Espionagem",
            "diceRangeMin": 4,
            "diceRangeMax": 4
        },
        "5-5": {
            "name": "Corrupção",
            "diceRangeMin": 5,
            "diceRangeMax": 5
        },
        "6-6": {
            "name": "Taxas abusivas",
            "diceRangeMin": 6,
            "diceRangeMax": 6
        },
        "7-7": {
            "name": "Líder manipulado",
            "diceRangeMin": 7,
            "diceRangeMax": 7
        },
        "8-8": {
            "name": "Odeiam forasteiros",
            "diceRangeMin": 8,
            "diceRangeMax": 8
        },
        "9-9": {
            "name": "Criminosos infiltrados",
            "diceRangeMin": 9,
            "diceRangeMax": 9
        },
        "10-10": {
            "name": "Cumprir o objetivo pode iniciar uma guerra",
            "diceRangeMin": 10,
            "diceRangeMax": 10
        }
    },
    "protection": {
        "1-1": {
            "name": "Guardado por uma criatura poderosa",
            "diceRangeMin": 1,
            "diceRangeMax": 1
        },
        "2-2": {
            "name": "Protegido por magias e maldições",
            "diceRangeMin": 2,
            "diceRangeMax": 2
        },
        "3-3": {
            "name": "Protegido por lei",
            "diceRangeMin": 3,
            "diceRangeMax": 3
        },
        "4-4": {
            "name": "Falha de segurança grave",
            "diceRangeMin": 4,
            "diceRangeMax": 4
        },
        "5-5": {
            "name": "Protegido por um elemental (gênio)",
            "diceRangeMin": 5,
            "diceRangeMax": 5
        },
        "6-6": {
            "name": "Selo celestial",
            "diceRangeMin": 6,
            "diceRangeMax": 6
        },
        "7-7": {
            "name": "Selo abissal/infernal",
            "diceRangeMin": 7,
            "diceRangeMax": 7
        },
        "8-8": {
            "name": "Construção anã antiga",
            "diceRangeMin": 8,
            "diceRangeMax": 8
        },
        "9-9": {
            "name": "Protegido por um dragão adormecido",
            "diceRangeMin": 9,
            "diceRangeMax": 9
        },
        "10-10": {
            "name": "Protegido por inocentes",
            "diceRangeMin": 10,
            "diceRangeMax": 10
        }
    },
    "friendlyAgainstTime": {
        "1-1": {
            "name": "Gnomos pregando peças",
            "diceRangeMin": 1,
            "diceRangeMax": 1
        },
        "2-2": {
            "name": "Um grande herói tem o objetivo contrário",
            "diceRangeMin": 2,
            "diceRangeMax": 2
        },
        "3-3": {
            "name": "Objetivo conflita com o ideal do contratado",
            "diceRangeMin": 3,
            "diceRangeMax": 3
        },
        "4-4": {
            "name": "Criaturas bondosas tentando fazer amizade",
            "diceRangeMin": 4,
            "diceRangeMax": 4
        },
        "5-5": {
            "name": "Humanoides atrapalham tentando ajudar",
            "diceRangeMin": 5,
            "diceRangeMax": 5
        },
        "6-6": {
            "name": "Inocente se entrega para salvar o culpado",
            "diceRangeMin": 6,
            "diceRangeMax": 6
        },
        "7-7": {
            "name": "Rival tenta duelar o tempo todo",
            "diceRangeMin": 7,
            "diceRangeMax": 7
        },
        "8-8": {
            "name": "Festividades e badernas que tiram o foco",
            "diceRangeMin": 8,
            "diceRangeMax": 8
        },
        "9-9": {
            "name": "Clérigos que evitam conflito",
            "diceRangeMin": 9,
            "diceRangeMax": 9
        },
        "10-10": {
            "name": "Contratante vai junto/manda um supervisor",
            "diceRangeMin": 10,
            "diceRangeMax": 10
        }
    },
    "hostileMeeting": {
        "1-1": {
            "name": "Acontece um encontro hostil adicional por dia",
            "diceRangeMin": 1,
            "diceRangeMax": 1
        },
        "2-2": {
            "name": "Pra cada encontro hostil, acontece mais um",
            "diceRangeMin": 2,
            "diceRangeMax": 2
        },
        "3-3": {
            "name": "A cada dois dias acontece um encontro hostil",
            "diceRangeMin": 3,
            "diceRangeMax": 3
        },
        "4-4": {
            "name": "Todo encontro é hostil",
            "diceRangeMin": 4,
            "diceRangeMax": 4
        },
        "5-5": {
            "name": "Se o encontro não for hostil, ele não acontece",
            "diceRangeMin": 5,
            "diceRangeMax": 5
        },
        "6-6": {
            "name": "Inimigos hostis são mais poderosos",
            "diceRangeMin": 6,
            "diceRangeMax": 6
        },
        "7-7": {
            "name": "Oponentes tendem a ficar hostis mais facilmente",
            "diceRangeMin": 7,
            "diceRangeMax": 7
        },
        "8-8": {
            "name": "Dobre os DVs de todos inimigos hostis",
            "diceRangeMin": 8,
            "diceRangeMax": 8
        },
        "9-9": {
            "name": "Inimigos hostis SEMPRE tem itens mágicos",
            "diceRangeMin": 9,
            "diceRangeMax": 9
        },
        "10-10": {
            "name": "Caso estejam perdendo fogem mas retornam para se vingar",
            "diceRangeMin": 10,
            "diceRangeMax": 10
        }
    }
}